{
  "source": "https://onlineradiobox.com/co/olmpicamedellin/playlist/2?cs=co.olmpicabogota",
  "scraped_at": "2025-08-24 11:52:44",
  "count": 368,
  "items": [
    {
      "time_played": "23:59",
      "artist": "LOS DESPECHADOS",
      "title": "DE QUE DUELE DUELE",
      "raw": "LOS DESPECHADOS - DE QUE DUELE DUELE",
      "link": "https://onlineradiobox.com/track/810249620622284970/"
    },
    {
      "time_played": "23:55",
      "artist": "EL BINOMIO DE ORO",
      "title": "DIME QUIEN.wav",
      "raw": "EL BINOMIO DE ORO - DIME QUIEN.wav",
      "link": null
    },
    {
      "time_played": "23:50",
      "artist": "MIGUEL MORALES",
      "title": "LA VERDAD DE TU AMOR.wav",
      "raw": "MIGUEL MORALES - LA VERDAD DE TU AMOR.wav",
      "link": "https://onlineradiobox.com/track/792780438649958285/"
    },
    {
      "time_played": "23:46",
      "artist": "VICENTE FERNANDEZ",
      "title": "MISERIA - .wav",
      "raw": "VICENTE FERNANDEZ - MISERIA - .wav",
      "link": "https://onlineradiobox.com/track/288394723241200149/"
    },
    {
      "time_played": "23:42",
      "artist": "LOS CHICHES VALLENATOS",
      "title": "TE VERE LLORAR",
      "raw": "LOS CHICHES VALLENATOS - TE VERE LLORAR",
      "link": "https://onlineradiobox.com/track/288394718822283261/"
    },
    {
      "time_played": "23:37",
      "artist": "LOS GIGANTES DEL VALLENATO",
      "title": "TE EXTRA?O TANTO.wav",
      "raw": "LOS GIGANTES DEL VALLENATO - TE EXTRA?O TANTO.wav",
      "link": null
    },
    {
      "time_played": "23:34",
      "artist": "LOS TIGRES DEL NORTE",
      "title": "NI PARIENTES SOMOS",
      "raw": "LOS TIGRES DEL NORTE - NI PARIENTES SOMOS",
      "link": "https://onlineradiobox.com/track/39387852/"
    },
    {
      "time_played": "23:29",
      "artist": "EL BINOMIO DE ORO",
      "title": "REALIZAME MIS SUE?OS",
      "raw": "EL BINOMIO DE ORO - REALIZAME MIS SUE?OS",
      "link": "https://onlineradiobox.com/track/738191845218847106/"
    },
    {
      "time_played": "23:24",
      "artist": "MICKEY TAVERAS",
      "title": "Y QUE ME PASA",
      "raw": "MICKEY TAVERAS - Y QUE ME PASA",
      "link": "https://onlineradiobox.com/track/288289365897687287/"
    },
    {
      "time_played": "23:20",
      "artist": "MIGUEL MORALES",
      "title": "QUE ME PUEDAS AMAR",
      "raw": "MIGUEL MORALES - QUE ME PUEDAS AMAR",
      "link": "https://onlineradiobox.com/track/144226755083353211/"
    },
    {
      "time_played": "23:15",
      "artist": "SILVIO BRITO",
      "title": "TU ERES EL AMOR",
      "raw": "SILVIO BRITO - TU ERES EL AMOR",
      "link": "https://onlineradiobox.com/track/233788702965800119/"
    },
    {
      "time_played": "23:11",
      "artist": "JORGE CELEDON",
      "title": "CUATRO ROSAS",
      "raw": "JORGE CELEDON - CUATRO ROSAS",
      "link": "https://onlineradiobox.com/track/1801551568805413268/"
    },
    {
      "time_played": "23:06",
      "artist": "SILVESTRE DANGON",
      "title": "COMO LO HIZO.wav",
      "raw": "SILVESTRE DANGON - COMO LO HIZO.wav",
      "link": null
    },
    {
      "time_played": "23:06",
      "artist": "PASTOR LOPEZ",
      "title": "Jingle Escuchando OLP Largo.wav",
      "raw": "PASTOR LOPEZ - Jingle Escuchando OLP Largo.wav",
      "link": null
    },
    {
      "time_played": "23:00",
      "artist": "LOS RELICARIOS",
      "title": "MUJER TRAIDORA",
      "raw": "LOS RELICARIOS - MUJER TRAIDORA",
      "link": "https://onlineradiobox.com/track/1441298637658311462/"
    },
    {
      "time_played": "22:58",
      "artist": "PASTOR LOPEZ",
      "title": "MI CATRA FINA",
      "raw": "PASTOR LOPEZ - MI CATRA FINA",
      "link": null
    },
    {
      "time_played": "22:53",
      "artist": "LUIS MIGUEL FUENTES.",
      "title": "INALCANZABLE",
      "raw": "LUIS MIGUEL FUENTES. - INALCANZABLE",
      "link": "https://onlineradiobox.com/track/882307063111700493/"
    },
    {
      "time_played": "22:50",
      "artist": "JULIO JARAMILLO",
      "title": "CINCO CENTAVITOS",
      "raw": "JULIO JARAMILLO - CINCO CENTAVITOS",
      "link": "https://onlineradiobox.com/track/161731254808952101/"
    },
    {
      "time_played": "22:45",
      "artist": "BINOMIO DE ORO",
      "title": "DIME PAJARITO",
      "raw": "BINOMIO DE ORO - DIME PAJARITO",
      "link": "https://onlineradiobox.com/track/2089852558648544044/"
    },
    {
      "time_played": "22:43",
      "artist": "JOAN SEBASTIAN",
      "title": "LOBO DOMESTICADO",
      "raw": "JOAN SEBASTIAN - LOBO DOMESTICADO",
      "link": "https://onlineradiobox.com/track/1170537506607772355/"
    },
    {
      "time_played": "22:39",
      "artist": "LUISITO MU?OZ",
      "title": "MI MAS GRANDE LOCURA",
      "raw": "LUISITO MU?OZ - MI MAS GRANDE LOCURA",
      "link": "https://onlineradiobox.com/track/2161839358471612388/"
    },
    {
      "time_played": "22:36",
      "artist": "JHONNY RIVERA",
      "title": "EL DOLOR DE UNA PARTIDA",
      "raw": "JHONNY RIVERA - EL DOLOR DE UNA PARTIDA",
      "link": "https://onlineradiobox.com/track/432509910195238731/"
    },
    {
      "time_played": "22:31",
      "artist": "EMBRUJO VALLENATO",
      "title": "LA ULTIMA NOCHE",
      "raw": "EMBRUJO VALLENATO - LA ULTIMA NOCHE",
      "link": "https://onlineradiobox.com/track/720652690972121106/"
    },
    {
      "time_played": "22:28",
      "artist": "EL GRAN DAVID",
      "title": "PALOMA DEL ALMA MIA",
      "raw": "EL GRAN DAVID - PALOMA DEL ALMA MIA",
      "link": "https://onlineradiobox.com/track/792797881253286457/"
    },
    {
      "time_played": "22:25",
      "artist": "VICENTE FERNANDEZ",
      "title": "PARA SIEMPRE",
      "raw": "VICENTE FERNANDEZ - PARA SIEMPRE",
      "link": "https://onlineradiobox.com/track/33166372/"
    },
    {
      "time_played": "22:20",
      "artist": "EMBRUJO VALLENATO",
      "title": "LA ULTIMA NOCHE",
      "raw": "EMBRUJO VALLENATO - LA ULTIMA NOCHE",
      "link": "https://onlineradiobox.com/track/720652690972121106/"
    },
    {
      "time_played": "22:14",
      "artist": "ALEX BUENO",
      "title": "JARDIN PROHIBIDO - .wav",
      "raw": "ALEX BUENO - JARDIN PROHIBIDO - .wav",
      "link": null
    },
    {
      "time_played": "22:09",
      "artist": "LOS INQUIETOS DEL VALLENATO",
      "title": "SUAVE BRISA",
      "raw": "LOS INQUIETOS DEL VALLENATO - SUAVE BRISA",
      "link": "https://onlineradiobox.com/track/2089816985266207141/"
    },
    {
      "time_played": "22:05",
      "artist": "JUAN CARLOS ANDARIEGO",
      "title": "AMOR OCULTO",
      "raw": "JUAN CARLOS ANDARIEGO - AMOR OCULTO",
      "link": null
    },
    {
      "time_played": "22:00",
      "artist": "ROMUALDO BRITO",
      "title": "TATUAJE EN EL ALMA",
      "raw": "ROMUALDO BRITO - TATUAJE EN EL ALMA",
      "link": "https://onlineradiobox.com/track/288359573824484475/"
    },
    {
      "time_played": "21:57",
      "artist": "MIGUEL GALLARDO",
      "title": "MUCHACHITA",
      "raw": "MIGUEL GALLARDO - MUCHACHITA",
      "link": "https://onlineradiobox.com/track/1513303792654013915/"
    },
    {
      "time_played": "21:53",
      "artist": "JOAQUIN GUILLER & MAICOL ROSERO",
      "title": "NO SUFRIRE POR NADIE",
      "raw": "JOAQUIN GUILLER & MAICOL ROSERO - NO SUFRIRE POR NADIE",
      "link": null
    },
    {
      "time_played": "21:49",
      "artist": "DIOMEDES D AZ.",
      "title": "DEJAME LLORAR",
      "raw": "DIOMEDES D AZ. - DEJAME LLORAR",
      "link": null
    },
    {
      "time_played": "21:46",
      "artist": "PASTOR LOPEZ",
      "title": "DONDE ESTAS",
      "raw": "PASTOR LOPEZ - DONDE ESTAS",
      "link": "https://onlineradiobox.com/track/216337125355805647/"
    },
    {
      "time_played": "21:42",
      "artist": "DIOMEDES DIAZ",
      "title": "ILUSIONES",
      "raw": "DIOMEDES DIAZ - ILUSIONES",
      "link": "https://onlineradiobox.com/track/2251401328790265332/"
    },
    {
      "time_played": "21:38",
      "artist": "SEGUNDO ROSERO",
      "title": "COMO VOY A OLVIDARTE",
      "raw": "SEGUNDO ROSERO - COMO VOY A OLVIDARTE",
      "link": "https://onlineradiobox.com/track/1170537579615511272/"
    },
    {
      "time_played": "21:34",
      "artist": "RAFAEL OROZCO",
      "title": "DE RODILLAS.wav",
      "raw": "RAFAEL OROZCO - DE RODILLAS.wav",
      "link": null
    },
    {
      "time_played": "21:31",
      "artist": "LORENZO ANTONIO",
      "title": "DOCE ROSAS",
      "raw": "LORENZO ANTONIO - DOCE ROSAS",
      "link": "https://onlineradiobox.com/track/38097119/"
    },
    {
      "time_played": "21:26",
      "artist": "LOS GIGANTES DEL VALLENATO",
      "title": "VETE DE MI.wav",
      "raw": "LOS GIGANTES DEL VALLENATO - VETE DE MI.wav",
      "link": "https://onlineradiobox.com/track/1314653337966371092/"
    },
    {
      "time_played": "21:23",
      "artist": "LOS RAYOS",
      "title": "CRUZ DE MADERA",
      "raw": "LOS RAYOS - CRUZ DE MADERA",
      "link": "https://onlineradiobox.com/track/1513321012790465254/"
    },
    {
      "time_played": "21:18",
      "artist": "EL BINOMIO DE ORO",
      "title": "MIS HOJAS SECAS",
      "raw": "EL BINOMIO DE ORO - MIS HOJAS SECAS",
      "link": "https://onlineradiobox.com/track/1585378673039291135/"
    },
    {
      "time_played": "21:14",
      "artist": "EDDIE SANTIAGO",
      "title": "HASTA AQUI TE FUI FIEL - .wav",
      "raw": "EDDIE SANTIAGO - HASTA AQUI TE FUI FIEL - .wav",
      "link": "https://onlineradiobox.com/track/1945719438048940685/"
    },
    {
      "time_played": "21:09",
      "artist": "LOS DIABLITOS",
      "title": "QUE NUNCA ME FALTES TU.wav",
      "raw": "LOS DIABLITOS - QUE NUNCA ME FALTES TU.wav",
      "link": null
    },
    {
      "time_played": "21:07",
      "artist": "LUIS ALBERTO POSADA",
      "title": "BASTA CON LICOR",
      "raw": "LUIS ALBERTO POSADA - BASTA CON LICOR",
      "link": "https://onlineradiobox.com/track/288429972621725904/"
    },
    {
      "time_played": "21:03",
      "artist": "LOS FANTASTICOS DEL VALLENATO",
      "title": "TE EXTRA?O",
      "raw": "LOS FANTASTICOS DEL VALLENATO - TE EXTRA?O",
      "link": "https://onlineradiobox.com/track/1152998252930192938/"
    },
    {
      "time_played": "21:00",
      "artist": "LOS CABALLEROSDE LA CANTINA",
      "title": "EL ENVIDIOSO.wav",
      "raw": "LOS CABALLEROSDE LA CANTINA - EL ENVIDIOSO.wav",
      "link": "https://onlineradiobox.com/track/827877634212482460/"
    },
    {
      "time_played": "20:56",
      "artist": "JORGE CELEDON",
      "title": "ME GUSTAS MUCHO",
      "raw": "JORGE CELEDON - ME GUSTAS MUCHO",
      "link": "https://onlineradiobox.com/track/1674940584977972434/"
    },
    {
      "time_played": "20:53",
      "artist": "CIRO QUI?ONEZ",
      "title": "REGALADA SALES CARA REMIX",
      "raw": "CIRO QUI?ONEZ - REGALADA SALES CARA REMIX",
      "link": null
    },
    {
      "time_played": "20:48",
      "artist": "EL BINOMIO DE ORO",
      "title": "NO PUDE OLVIDARTE",
      "raw": "EL BINOMIO DE ORO - NO PUDE OLVIDARTE",
      "link": "https://onlineradiobox.com/track/377903935167320300/"
    },
    {
      "time_played": "20:44",
      "artist": "EDGAR LEANDRO",
      "title": "PAGARAS",
      "raw": "EDGAR LEANDRO - PAGARAS",
      "link": "https://onlineradiobox.com/track/1008847465947406449/"
    },
    {
      "time_played": "20:40",
      "artist": "ERICK ESCOBAR Y LA DECISION VALLENATA",
      "title": "NO PUDE QUITARTE LAS ESPINAS",
      "raw": "ERICK ESCOBAR Y LA DECISION VALLENATA - NO PUDE QUITARTE LAS ESPINAS",
      "link": "https://onlineradiobox.com/track/1530825394476781234/"
    },
    {
      "time_played": "20:37",
      "artist": "JAVIER SOLIS",
      "title": "TE AMARE TODA LA VIDA",
      "raw": "JAVIER SOLIS - TE AMARE TODA LA VIDA",
      "link": "https://onlineradiobox.com/track/59448388/"
    },
    {
      "time_played": "20:33",
      "artist": "LOS HERMANOS NARANJO",
      "title": "TU AUSENCIA",
      "raw": "LOS HERMANOS NARANJO - TU AUSENCIA",
      "link": "https://onlineradiobox.com/track/144244350208793531/"
    },
    {
      "time_played": "20:29",
      "artist": "FRANCO DEVITA",
      "title": "TE AMO",
      "raw": "FRANCO DEVITA - TE AMO",
      "link": "https://onlineradiobox.com/track/680011/"
    },
    {
      "time_played": "20:22",
      "artist": "LOS CABALLEROS DE LA CANTINA",
      "title": "AMIGO EL RATON DEL QUESO",
      "raw": "LOS CABALLEROS DE LA CANTINA - AMIGO EL RATON DEL QUESO",
      "link": "https://onlineradiobox.com/track/1513250893174041183/"
    },
    {
      "time_played": "20:18",
      "artist": "LOS CHICHES VALLENATOS",
      "title": "CENIZA FRIA",
      "raw": "LOS CHICHES VALLENATOS - CENIZA FRIA",
      "link": "https://onlineradiobox.com/track/864714986089848915/"
    },
    {
      "time_played": "20:12",
      "artist": "GRUPO NICHE",
      "title": "NUESTRO SUE?O",
      "raw": "GRUPO NICHE - NUESTRO SUE?O",
      "link": "https://onlineradiobox.com/track/2233897007879191468/"
    },
    {
      "time_played": "20:07",
      "artist": "LOS INQUIETOS DEL VALLENATO",
      "title": "REGALAME UNA NOCHE",
      "raw": "LOS INQUIETOS DEL VALLENATO - REGALAME UNA NOCHE",
      "link": "https://onlineradiobox.com/track/2251401566015626928/"
    },
    {
      "time_played": "20:03",
      "artist": "VICENTE FERNANDEZ",
      "title": "NOS ESTORBO LA ROPA",
      "raw": "VICENTE FERNANDEZ - NOS ESTORBO LA ROPA",
      "link": "https://onlineradiobox.com/track/41290809/"
    },
    {
      "time_played": "20:00",
      "artist": "ROMUALDO BRITO",
      "title": "EMBRUJO",
      "raw": "ROMUALDO BRITO - EMBRUJO",
      "link": "https://onlineradiobox.com/track/576607697065750954/"
    },
    {
      "time_played": "19:56",
      "artist": "LOS BUKIS",
      "title": "TU CARCEL.wav",
      "raw": "LOS BUKIS - TU CARCEL.wav",
      "link": "https://onlineradiobox.com/track/1386710695865160709/"
    },
    {
      "time_played": "19:51",
      "artist": "DIOMEDES DIAZ Y JUANCHO ROIS",
      "title": "DOBLARON CAMPANAS",
      "raw": "DIOMEDES DIAZ Y JUANCHO ROIS - DOBLARON CAMPANAS",
      "link": null
    },
    {
      "time_played": "19:48",
      "artist": "EL ANDARIEGO",
      "title": "LA FOTO DE LOS DOS",
      "raw": "EL ANDARIEGO - LA FOTO DE LOS DOS",
      "link": "https://onlineradiobox.com/track/1585449125164510820/"
    },
    {
      "time_played": "19:43",
      "artist": "LA COMBINACION VALLENATA",
      "title": "QUE ME PERDONE",
      "raw": "LA COMBINACION VALLENATA - QUE ME PERDONE",
      "link": "https://onlineradiobox.com/track/1513356233858650810/"
    },
    {
      "time_played": "19:38",
      "artist": "HERNAN HERNANDEZ.",
      "title": "ADIOS AL AMOR",
      "raw": "HERNAN HERNANDEZ. - ADIOS AL AMOR",
      "link": "https://onlineradiobox.com/track/1441298773602923855/"
    },
    {
      "time_played": "19:34",
      "artist": "EMBRUJO VALLENATO",
      "title": "FUE POR ELLA",
      "raw": "EMBRUJO VALLENATO - FUE POR ELLA",
      "link": "https://onlineradiobox.com/track/1188165310026355121/"
    },
    {
      "time_played": "19:29",
      "artist": "JOAN SEBASTIAN",
      "title": "SECRETO DE AMOR.wav",
      "raw": "JOAN SEBASTIAN - SECRETO DE AMOR.wav",
      "link": "https://onlineradiobox.com/track/1657366307249251797/"
    },
    {
      "time_played": "19:25",
      "artist": "BINOMIO DE ORO",
      "title": "NOSTALGIA",
      "raw": "BINOMIO DE ORO - NOSTALGIA",
      "link": "https://onlineradiobox.com/track/37084225/"
    },
    {
      "time_played": "19:21",
      "artist": "DARIO GOMEZ",
      "title": "TIRANA",
      "raw": "DARIO GOMEZ - TIRANA",
      "link": "https://onlineradiobox.com/track/2179343859921388066/"
    },
    {
      "time_played": "19:16",
      "artist": "LOS GIGANTES DEL VALLENATO",
      "title": "ACUERDATE",
      "raw": "LOS GIGANTES DEL VALLENATO - ACUERDATE",
      "link": "https://onlineradiobox.com/track/648595162680369274/"
    },
    {
      "time_played": "19:11",
      "artist": "VICTOR MANUEL.",
      "title": "VOY A PROMETERME",
      "raw": "VICTOR MANUEL. - VOY A PROMETERME",
      "link": "https://onlineradiobox.com/track/2089817025627563240/"
    },
    {
      "time_played": "19:06",
      "artist": "EL BINOMIO DE ORO",
      "title": "DEJATE ATRAPAR.wav",
      "raw": "EL BINOMIO DE ORO - DEJATE ATRAPAR.wav",
      "link": "https://onlineradiobox.com/track/1513373833630174865/"
    },
    {
      "time_played": "19:03",
      "artist": "ALZATE",
      "title": "AMOR VERDADERO",
      "raw": "ALZATE - AMOR VERDADERO",
      "link": "https://onlineradiobox.com/track/1008970667553924546/"
    },
    {
      "time_played": "18:58",
      "artist": "MIGUEL MORALES",
      "title": "SOLO ME FALTABAS TU",
      "raw": "MIGUEL MORALES - SOLO ME FALTABAS TU",
      "link": "https://onlineradiobox.com/track/864855479159522593/"
    },
    {
      "time_played": "18:53",
      "artist": "ANA GABRIEL",
      "title": "BESOS PROHIBIDOS",
      "raw": "ANA GABRIEL - BESOS PROHIBIDOS",
      "link": "https://onlineradiobox.com/track/97574967/"
    },
    {
      "time_played": "18:48",
      "artist": "EL BINOMIO DE ORO",
      "title": "ME VAS A EXTRA?AR",
      "raw": "EL BINOMIO DE ORO - ME VAS A EXTRA?AR",
      "link": "https://onlineradiobox.com/track/1369205879063344366/"
    },
    {
      "time_played": "18:44",
      "artist": "HEREDERO",
      "title": "COQUETA",
      "raw": "HEREDERO - COQUETA",
      "link": "https://onlineradiobox.com/track/2089712510846799729/"
    },
    {
      "time_played": "18:40",
      "artist": "RAFAEL OROZCO",
      "title": "SOLO PARA TI.wav",
      "raw": "RAFAEL OROZCO - SOLO PARA TI.wav",
      "link": null
    },
    {
      "time_played": "18:36",
      "artist": "LOS DANDY",
      "title": "POBRE SOY",
      "raw": "LOS DANDY - POBRE SOY",
      "link": "https://onlineradiobox.com/track/432492362967231252/"
    },
    {
      "time_played": "18:32",
      "artist": "LUIS MIGUEL FUENTES.",
      "title": "MALDITA VIDA SIN TI",
      "raw": "LUIS MIGUEL FUENTES. - MALDITA VIDA SIN TI",
      "link": "https://onlineradiobox.com/track/144226739456643097/"
    },
    {
      "time_played": "18:28",
      "artist": "ORLANDO CONTRERAS",
      "title": "SIN EGOISMO",
      "raw": "ORLANDO CONTRERAS - SIN EGOISMO",
      "link": "https://onlineradiobox.com/track/93942357583923/"
    },
    {
      "time_played": "18:23",
      "artist": "LOS GIGANTES DEL VALLENATO",
      "title": "OTRO DIA SERA.wav",
      "raw": "LOS GIGANTES DEL VALLENATO - OTRO DIA SERA.wav",
      "link": "https://onlineradiobox.com/track/360470145253594131/"
    },
    {
      "time_played": "18:20",
      "artist": "JOAN SEBASTIAN",
      "title": "RUMORES",
      "raw": "JOAN SEBASTIAN - RUMORES",
      "link": "https://onlineradiobox.com/track/2251401352340206011/"
    },
    {
      "time_played": "18:15",
      "artist": "MIGUEL MORALES",
      "title": "DOS SENTMIENTOS",
      "raw": "MIGUEL MORALES - DOS SENTMIENTOS",
      "link": null
    },
    {
      "time_played": "18:12",
      "artist": "DARIO GOMEZ",
      "title": "CONTRA VIENTO Y MAREA",
      "raw": "DARIO GOMEZ - CONTRA VIENTO Y MAREA",
      "link": "https://onlineradiobox.com/track/2089834576691497827/"
    },
    {
      "time_played": "18:07",
      "artist": "OTTO SERGE",
      "title": "TU",
      "raw": "OTTO SERGE - TU",
      "link": "https://onlineradiobox.com/track/792657428846291652/"
    },
    {
      "time_played": "18:04",
      "artist": "ALEJANDRO FERNANDEZ.",
      "title": "MATALAS",
      "raw": "ALEJANDRO FERNANDEZ. - MATALAS",
      "link": "https://onlineradiobox.com/track/40880926/"
    },
    {
      "time_played": "18:00",
      "artist": "LOS DIABLITOS",
      "title": "A BESITOS.wav",
      "raw": "LOS DIABLITOS - A BESITOS.wav",
      "link": "https://onlineradiobox.com/track/611704638641390734/"
    },
    {
      "time_played": "17:58",
      "artist": "ORESTE SINDICE",
      "title": "HIMNO NACIONAL DE COLOMBIA",
      "raw": "ORESTE SINDICE - HIMNO NACIONAL DE COLOMBIA",
      "link": null
    },
    {
      "time_played": "17:53",
      "artist": "PIPE BUENO",
      "title": "TE HUBIERAS IDO ANTES",
      "raw": "PIPE BUENO - TE HUBIERAS IDO ANTES",
      "link": "https://onlineradiobox.com/track/1891113490514882562/"
    },
    {
      "time_played": "17:46",
      "artist": "LOS INFIELES",
      "title": "ENSE?AME A OLVIDAR - .wav",
      "raw": "LOS INFIELES - ENSE?AME A OLVIDAR - .wav",
      "link": null
    },
    {
      "time_played": "17:44",
      "artist": "VICENTE FERNANDEZ",
      "title": "NO ME SE RAJAR",
      "raw": "VICENTE FERNANDEZ - NO ME SE RAJAR",
      "link": "https://onlineradiobox.com/track/54883690/"
    },
    {
      "time_played": "17:40",
      "artist": "SILVIO BRITO",
      "title": "HISTORIA DE AMOR",
      "raw": "SILVIO BRITO - HISTORIA DE AMOR",
      "link": "https://onlineradiobox.com/track/792762704451592474/"
    },
    {
      "time_played": "17:36",
      "artist": "GALI GALIANO",
      "title": "AMOR DE PRIMAVERA",
      "raw": "GALI GALIANO - AMOR DE PRIMAVERA",
      "link": "https://onlineradiobox.com/track/2017654213101402047/"
    },
    {
      "time_played": "17:32",
      "artist": "LOS GIGANTES DEL VALLENATO",
      "title": "QUE LE DIRE AL CORAZON",
      "raw": "LOS GIGANTES DEL VALLENATO - QUE LE DIRE AL CORAZON",
      "link": "https://onlineradiobox.com/track/288306724738015114/"
    },
    {
      "time_played": "17:28",
      "artist": "DARIO GOMEZ",
      "title": "DECIDELO",
      "raw": "DARIO GOMEZ - DECIDELO",
      "link": "https://onlineradiobox.com/track/1945701805452458939/"
    },
    {
      "time_played": "17:24",
      "artist": "EL BINOMIO DE ORO",
      "title": "REALIZAME MIS SUE?OS",
      "raw": "EL BINOMIO DE ORO - REALIZAME MIS SUE?OS",
      "link": "https://onlineradiobox.com/track/738191845218847106/"
    },
    {
      "time_played": "17:21",
      "artist": "JOHANNY AYALA",
      "title": "PIENSA EN MI",
      "raw": "JOHANNY AYALA - PIENSA EN MI",
      "link": null
    },
    {
      "time_played": "17:16",
      "artist": "LOS DIABLITOS",
      "title": "SIRENA ENCANTADA",
      "raw": "LOS DIABLITOS - SIRENA ENCANTADA",
      "link": "https://onlineradiobox.com/track/1297201051229341773/"
    },
    {
      "time_played": "17:13",
      "artist": "LOS RAYOS",
      "title": "CRUZ DE MADERA",
      "raw": "LOS RAYOS - CRUZ DE MADERA",
      "link": "https://onlineradiobox.com/track/1513321012790465254/"
    },
    {
      "time_played": "17:09",
      "artist": "LOS RAYOS",
      "title": "BILLETE VERDE",
      "raw": "LOS RAYOS - BILLETE VERDE",
      "link": "https://onlineradiobox.com/track/2161909846601343265/"
    },
    {
      "time_played": "17:06",
      "artist": "ARMANDO HERNANDEZ",
      "title": "SIN RENCORES",
      "raw": "ARMANDO HERNANDEZ - SIN RENCORES",
      "link": "https://onlineradiobox.com/track/2161856971505473344/"
    },
    {
      "time_played": "16:57",
      "artist": "BANANAS",
      "title": "TE EXTRA?O",
      "raw": "BANANAS - TE EXTRA?O",
      "link": "https://onlineradiobox.com/track/1585378656720941962/"
    },
    {
      "time_played": "16:52",
      "artist": "LOS INQUIETOS DEL VALLENATO",
      "title": "QUIERO SABER DE TI",
      "raw": "LOS INQUIETOS DEL VALLENATO - QUIERO SABER DE TI",
      "link": "https://onlineradiobox.com/track/1945631734263810159/"
    },
    {
      "time_played": "16:48",
      "artist": "JOAQUIN GUILLER & MAICOL ROSERO",
      "title": "NO SUFRIRE POR NADIE",
      "raw": "JOAQUIN GUILLER & MAICOL ROSERO - NO SUFRIRE POR NADIE",
      "link": null
    },
    {
      "time_played": "16:43",
      "artist": "JOSE LUIS CARRASCAL",
      "title": "COMO DUELE EL FRIO",
      "raw": "JOSE LUIS CARRASCAL - COMO DUELE EL FRIO",
      "link": "https://onlineradiobox.com/track/360434728619082792/"
    },
    {
      "time_played": "16:39",
      "artist": "RUBBY PEREZ",
      "title": "BUSCANDO TUS BESOS",
      "raw": "RUBBY PEREZ - BUSCANDO TUS BESOS",
      "link": "https://onlineradiobox.com/track/1746998185767600056/"
    },
    {
      "time_played": "16:35",
      "artist": "DIOMEDES DIAZ",
      "title": "LOS RECUERDOS DE ELLA",
      "raw": "DIOMEDES DIAZ - LOS RECUERDOS DE ELLA",
      "link": "https://onlineradiobox.com/track/144226732377477464/"
    },
    {
      "time_played": "16:29",
      "artist": "NELSON",
      "title": "LONDRES",
      "raw": "NELSON - LONDRES",
      "link": null
    },
    {
      "time_played": "16:25",
      "artist": "PASTOR LOPEZ",
      "title": "NUESTRO ANILLITO",
      "raw": "PASTOR LOPEZ - NUESTRO ANILLITO",
      "link": "https://onlineradiobox.com/track/1729564392732090147/"
    },
    {
      "time_played": "16:21",
      "artist": "LOS CANTANTES",
      "title": "NO HAY PESOS",
      "raw": "LOS CANTANTES - NO HAY PESOS",
      "link": "https://onlineradiobox.com/track/41188654/"
    },
    {
      "time_played": "16:17",
      "artist": "MARCO ANTONIO SOLIS",
      "title": "MAS QUE TU AMIGO",
      "raw": "MARCO ANTONIO SOLIS - MAS QUE TU AMIGO",
      "link": "https://onlineradiobox.com/track/2089764152832048469/"
    },
    {
      "time_played": "16:14",
      "artist": "LUIS ALFONSO",
      "title": "CHISMOFILIA",
      "raw": "LUIS ALFONSO - CHISMOFILIA",
      "link": "https://onlineradiobox.com/track/2233880412603096084/"
    },
    {
      "time_played": "16:12",
      "artist": "DANIEL SANTOS",
      "title": "TOMA JABON PA QUE LAVES",
      "raw": "DANIEL SANTOS - TOMA JABON PA QUE LAVES",
      "link": "https://onlineradiobox.com/track/720758064960388408/"
    },
    {
      "time_played": "16:09",
      "artist": "DARIO GOMEZ",
      "title": "ARREGLA PA QUE TE VAS",
      "raw": "DARIO GOMEZ - ARREGLA PA QUE TE VAS",
      "link": "https://onlineradiobox.com/track/1585413833031577096/"
    },
    {
      "time_played": "16:05",
      "artist": "OTTO SERGE YRAFAEL RICARDO",
      "title": "SE?ORA",
      "raw": "OTTO SERGE YRAFAEL RICARDO - SE?ORA",
      "link": "https://onlineradiobox.com/track/2035228613320288366/"
    },
    {
      "time_played": "16:01",
      "artist": "EL CHARRITO NEGRO",
      "title": "CON UN ADIOS - .wav",
      "raw": "EL CHARRITO NEGRO - CON UN ADIOS - .wav",
      "link": "https://onlineradiobox.com/track/666134813484081814/"
    },
    {
      "time_played": "15:57",
      "artist": "CUARTETO CONTINENTAL",
      "title": "LLORANDO SE FUE",
      "raw": "CUARTETO CONTINENTAL - LLORANDO SE FUE",
      "link": "https://onlineradiobox.com/track/2089816988478981799/"
    },
    {
      "time_played": "15:49",
      "artist": "LA DECISION VALLENATA",
      "title": "AMOR SIN FRONTERAS..wav",
      "raw": "LA DECISION VALLENATA - AMOR SIN FRONTERAS..wav",
      "link": "https://onlineradiobox.com/track/738192012527779597/"
    },
    {
      "time_played": "15:45",
      "artist": "FERNANDO BURBANO",
      "title": "AHORA QUE PUEDO",
      "raw": "FERNANDO BURBANO - AHORA QUE PUEDO",
      "link": "https://onlineradiobox.com/track/1513356235724076375/"
    },
    {
      "time_played": "15:42",
      "artist": "DIOMEDES DIAZ",
      "title": "SIMULACION",
      "raw": "DIOMEDES DIAZ - SIMULACION",
      "link": "https://onlineradiobox.com/track/216319540248515305/"
    },
    {
      "time_played": "15:37",
      "artist": "WILLIE COLON",
      "title": "IDILIO",
      "raw": "WILLIE COLON - IDILIO",
      "link": "https://onlineradiobox.com/track/1225143478371200573/"
    },
    {
      "time_played": "15:34",
      "artist": "ANTONIO AGUILAR",
      "title": "CABALLO DE PATAS BLANCAS",
      "raw": "ANTONIO AGUILAR - CABALLO DE PATAS BLANCAS",
      "link": "https://onlineradiobox.com/track/1441281012489530412/"
    },
    {
      "time_played": "15:29",
      "artist": "LOS DIABLITOS",
      "title": "HISTORIA.wav",
      "raw": "LOS DIABLITOS - HISTORIA.wav",
      "link": "https://onlineradiobox.com/track/1891113954110721706/"
    },
    {
      "time_played": "15:25",
      "artist": "LUIS ALBERTO POSADA",
      "title": "A TU PIEL",
      "raw": "LUIS ALBERTO POSADA - A TU PIEL",
      "link": "https://onlineradiobox.com/track/1081010664138851033/"
    },
    {
      "time_played": "15:21",
      "artist": "LUIS ALBERTO POSADA",
      "title": "SEDUCTORA EXPLOTADORA Y ALGO MAS",
      "raw": "LUIS ALBERTO POSADA - SEDUCTORA EXPLOTADORA Y ALGO MAS",
      "link": "https://onlineradiobox.com/track/432545160703198180/"
    },
    {
      "time_played": "15:17",
      "artist": "TROPICOMBO",
      "title": "TORMENTA",
      "raw": "TROPICOMBO - TORMENTA",
      "link": "https://onlineradiobox.com/track/504585231727327337/"
    },
    {
      "time_played": "15:12",
      "artist": "EDDY HERRERA",
      "title": "A DORMIR JUNTITOS",
      "raw": "EDDY HERRERA - A DORMIR JUNTITOS",
      "link": "https://onlineradiobox.com/track/35248995/"
    },
    {
      "time_played": "15:09",
      "artist": "YEISON JIMENEZ",
      "title": "MALDITA TRAGA",
      "raw": "YEISON JIMENEZ - MALDITA TRAGA",
      "link": "https://onlineradiobox.com/track/2089852506617390488/"
    },
    {
      "time_played": "15:05",
      "artist": "LOS BETOS",
      "title": "LA GEMELA",
      "raw": "LOS BETOS - LA GEMELA",
      "link": "https://onlineradiobox.com/track/72186754820926406/"
    },
    {
      "time_played": "15:01",
      "artist": "JUAN CARLOS HURTADO EL ANDARIEGO",
      "title": "EL AMOR NO TIENE EDAD",
      "raw": "JUAN CARLOS HURTADO EL ANDARIEGO - EL AMOR NO TIENE EDAD",
      "link": "https://onlineradiobox.com/track/1657524270900431016/"
    },
    {
      "time_played": "14:57",
      "artist": "EL GRAN COMBO DE PUERTO RICO",
      "title": "TE REGALO EL CORAZON",
      "raw": "EL GRAN COMBO DE PUERTO RICO - TE REGALO EL CORAZON",
      "link": "https://onlineradiobox.com/track/576554724037023904/"
    },
    {
      "time_played": "14:49",
      "artist": "ARMANDO HERNANDEZ",
      "title": "POR RETENERTE",
      "raw": "ARMANDO HERNANDEZ - POR RETENERTE",
      "link": null
    },
    {
      "time_played": "14:46",
      "artist": "DARIO GOMEZ",
      "title": "LA PENA ES HONDA",
      "raw": "DARIO GOMEZ - LA PENA ES HONDA",
      "link": "https://onlineradiobox.com/track/1873644195642359911/"
    },
    {
      "time_played": "14:41",
      "artist": "JOAQUIN GUILLER",
      "title": "EL AGROPECUARIO",
      "raw": "JOAQUIN GUILLER - EL AGROPECUARIO",
      "link": "https://onlineradiobox.com/track/432440662857722574/"
    },
    {
      "time_played": "14:36",
      "artist": "LOS INQUIETOS DEL VALLENATO",
      "title": "SI TU ESTUVIERAS",
      "raw": "LOS INQUIETOS DEL VALLENATO - SI TU ESTUVIERAS",
      "link": "https://onlineradiobox.com/track/72204353775993496/"
    },
    {
      "time_played": "14:33",
      "artist": "ALEXIS ESCOBAR feat Johnny Rivera",
      "title": "John Alex casta?o - LA SANTA Y LA DIABLA REMIX",
      "raw": "ALEXIS ESCOBAR feat Johnny Rivera - John Alex casta?o - LA SANTA Y LA DIABLA REMIX",
      "link": "https://onlineradiobox.com/track/1530825937909973257/"
    },
    {
      "time_played": "14:27",
      "artist": "LA COMBINACION VALLENATA Y JEAN CARLOS CENTENO",
      "title": "- QUE PENA -",
      "raw": "LA COMBINACION VALLENATA Y JEAN CARLOS CENTENO - - QUE PENA -",
      "link": "https://onlineradiobox.com/track/2233949760145686773/"
    },
    {
      "time_played": "14:24",
      "artist": "JESSI URIBE",
      "title": "MATEMOS LAS GANAS",
      "raw": "JESSI URIBE - MATEMOS LAS GANAS",
      "link": "https://onlineradiobox.com/track/449961658291715690/"
    },
    {
      "time_played": "14:20",
      "artist": "EL BINOMIO DE ORO",
      "title": "BA?ARTE EN MIS SUE?OS.wav",
      "raw": "EL BINOMIO DE ORO - BA?ARTE EN MIS SUE?OS.wav",
      "link": "https://onlineradiobox.com/track/1098479887826303667/"
    },
    {
      "time_played": "14:16",
      "artist": "LOS CABALLEROS DE LA CANTINA",
      "title": "TOCO MADERA",
      "raw": "LOS CABALLEROS DE LA CANTINA - TOCO MADERA",
      "link": "https://onlineradiobox.com/track/216549295069900754/"
    },
    {
      "time_played": "14:12",
      "artist": "JOE ARROYO",
      "title": "LA NOCHE",
      "raw": "JOE ARROYO - LA NOCHE",
      "link": "https://onlineradiobox.com/track/1225161387010749029/"
    },
    {
      "time_played": "14:09",
      "artist": "LOS DE YOLOMBO",
      "title": "EL BOBO",
      "raw": "LOS DE YOLOMBO - EL BOBO",
      "link": "https://onlineradiobox.com/track/1242595222382381111/"
    },
    {
      "time_played": "14:02",
      "artist": "LOS DIABLITOS",
      "title": "QUE HAGO SI TE PIERDO",
      "raw": "LOS DIABLITOS - QUE HAGO SI TE PIERDO",
      "link": "https://onlineradiobox.com/track/864855476826249431/"
    },
    {
      "time_played": "13:58",
      "artist": "HERNAN HERNANDEZ",
      "title": "TONTO AMOR",
      "raw": "HERNAN HERNANDEZ - TONTO AMOR",
      "link": "https://onlineradiobox.com/track/1657471612616557908/"
    },
    {
      "time_played": "13:56",
      "artist": "DANIEL SANTOS",
      "title": "TOMA JABON PA QUE LAVES",
      "raw": "DANIEL SANTOS - TOMA JABON PA QUE LAVES",
      "link": "https://onlineradiobox.com/track/720758064960388408/"
    },
    {
      "time_played": "13:49",
      "artist": "LUISITO MU?OZ",
      "title": "UNA COPA DE MAS",
      "raw": "LUISITO MU?OZ - UNA COPA DE MAS",
      "link": null
    },
    {
      "time_played": "13:49",
      "artist": "DARIOGOMEZ",
      "title": "POR ESA MUJER.wav",
      "raw": "DARIOGOMEZ - POR ESA MUJER.wav",
      "link": null
    },
    {
      "time_played": "13:46",
      "artist": "LIZANDRO MEZA",
      "title": "AL CALOR DE TU PIEL",
      "raw": "LIZANDRO MEZA - AL CALOR DE TU PIEL",
      "link": "https://onlineradiobox.com/track/216301962680858822/"
    },
    {
      "time_played": "13:42",
      "artist": "EL ANDARIEGO",
      "title": "QUE EST?S BUSCANDO",
      "raw": "EL ANDARIEGO - QUE EST?S BUSCANDO",
      "link": "https://onlineradiobox.com/track/1242595272643334863/"
    },
    {
      "time_played": "13:39",
      "artist": "EL ANDARIEGO",
      "title": "ADICTO A TI",
      "raw": "EL ANDARIEGO - ADICTO A TI",
      "link": "https://onlineradiobox.com/track/2179343958865764358/"
    },
    {
      "time_played": "13:33",
      "artist": "ROCIO DURCAL",
      "title": "AMOR ETERNO",
      "raw": "ROCIO DURCAL - AMOR ETERNO",
      "link": "https://onlineradiobox.com/track/50257384/"
    },
    {
      "time_played": "13:33",
      "artist": "ARELYS HENAO",
      "title": "DOS COSAS",
      "raw": "ARELYS HENAO - DOS COSAS",
      "link": "https://onlineradiobox.com/track/936931030778390556/"
    },
    {
      "time_played": "13:29",
      "artist": "DARIO GOMEZ",
      "title": "DEBISTE SER MAS SINCERA",
      "raw": "DARIO GOMEZ - DEBISTE SER MAS SINCERA",
      "link": "https://onlineradiobox.com/track/864855478590657091/"
    },
    {
      "time_played": "13:25",
      "artist": "JOAQUIN BEDOYA",
      "title": "EL ANALFABETA",
      "raw": "JOAQUIN BEDOYA - EL ANALFABETA",
      "link": "https://onlineradiobox.com/track/1081063578675602547/"
    },
    {
      "time_played": "13:25",
      "artist": "GILDARDO MONTOYA",
      "title": "DELE POR AHI",
      "raw": "GILDARDO MONTOYA - DELE POR AHI",
      "link": "https://onlineradiobox.com/track/1225125899636482833/"
    },
    {
      "time_played": "13:22",
      "artist": "VICENTE FERNANDEZ",
      "title": "LA DIFERENCIA",
      "raw": "VICENTE FERNANDEZ - LA DIFERENCIA",
      "link": "https://onlineradiobox.com/track/53743526/"
    },
    {
      "time_played": "13:18",
      "artist": "VICENTE FERNANDEZ",
      "title": "BOHEMIO DE AFICCION",
      "raw": "VICENTE FERNANDEZ - BOHEMIO DE AFICCION",
      "link": "https://onlineradiobox.com/track/1801621882209520351/"
    },
    {
      "time_played": "13:18",
      "artist": "LOS DIABLITOS",
      "title": "TU AMOR ES UN MILAGRO",
      "raw": "LOS DIABLITOS - TU AMOR ES UN MILAGRO",
      "link": "https://onlineradiobox.com/track/1297201038568391530/"
    },
    {
      "time_played": "13:09",
      "artist": "ALFREDO GUTIERREZ",
      "title": "LA CARTA NO.3",
      "raw": "ALFREDO GUTIERREZ - LA CARTA NO.3",
      "link": "https://onlineradiobox.com/track/792762705293581707/"
    },
    {
      "time_played": "13:02",
      "artist": "YEISON JIMENEZ",
      "title": "NI TENGO NI NECESITO",
      "raw": "YEISON JIMENEZ - NI TENGO NI NECESITO",
      "link": "https://onlineradiobox.com/track/17616362686860467/"
    },
    {
      "time_played": "12:58",
      "artist": "DARIO GOMEZ",
      "title": "LA INDOMABLE",
      "raw": "DARIO GOMEZ - LA INDOMABLE",
      "link": "https://onlineradiobox.com/track/79565836/"
    },
    {
      "time_played": "12:55",
      "artist": "DARIO GOMEZ",
      "title": "TIRANA",
      "raw": "DARIO GOMEZ - TIRANA",
      "link": "https://onlineradiobox.com/track/2179343859921388066/"
    },
    {
      "time_played": "12:52",
      "artist": "EL CHICO JARAMILLO",
      "title": "VETE ALEJATE DE MI",
      "raw": "EL CHICO JARAMILLO - VETE ALEJATE DE MI",
      "link": "https://onlineradiobox.com/track/1746998589972812023/"
    },
    {
      "time_played": "12:49",
      "artist": "MAURICIO LOPEZ",
      "title": "AY QUE DALO",
      "raw": "MAURICIO LOPEZ - AY QUE DALO",
      "link": "https://onlineradiobox.com/track/1585449094554833855/"
    },
    {
      "time_played": "12:45",
      "artist": "VICENTE FERNANDEZ",
      "title": "AUNQUE MAL PAGEN ELLAS",
      "raw": "VICENTE FERNANDEZ - AUNQUE MAL PAGEN ELLAS",
      "link": "https://onlineradiobox.com/track/1530825646416986680/"
    },
    {
      "time_played": "12:41",
      "artist": "JOSE MOGOLLON",
      "title": "LA ENREDADERA.wav",
      "raw": "JOSE MOGOLLON - LA ENREDADERA.wav",
      "link": "https://onlineradiobox.com/track/2161804750196516084/"
    },
    {
      "time_played": "12:37",
      "artist": "ARMANDO HERNANDEZ",
      "title": "MI MORENITA",
      "raw": "ARMANDO HERNANDEZ - MI MORENITA",
      "link": "https://onlineradiobox.com/track/1891113383668369756/"
    },
    {
      "time_played": "12:34",
      "artist": "JORGE LUIS HORTUA",
      "title": "SE PIERDE O SE GANA",
      "raw": "JORGE LUIS HORTUA - SE PIERDE O SE GANA",
      "link": "https://onlineradiobox.com/track/720670164616831240/"
    },
    {
      "time_played": "12:31",
      "artist": "LUIS ALBERTO POSADA",
      "title": "BASTA CON LICOR",
      "raw": "LUIS ALBERTO POSADA - BASTA CON LICOR",
      "link": "https://onlineradiobox.com/track/288429972621725904/"
    },
    {
      "time_played": "12:29",
      "artist": "YEISON JIMENEZ",
      "title": "EL MEJOR CABALLO",
      "raw": "YEISON JIMENEZ - EL MEJOR CABALLO",
      "link": "https://onlineradiobox.com/track/17616062401732340/"
    },
    {
      "time_played": "12:28",
      "artist": "RODOLFO CON LOS HISPANOS",
      "title": "BOTELLITA DE RON",
      "raw": "RODOLFO CON LOS HISPANOS - BOTELLITA DE RON",
      "link": "https://onlineradiobox.com/track/1369205927834256921/"
    },
    {
      "time_played": "12:24",
      "artist": "EL COMBO DE LAS ESTRELLAS",
      "title": "SOLEDAD",
      "raw": "EL COMBO DE LAS ESTRELLAS - SOLEDAD",
      "link": "https://onlineradiobox.com/track/1873591386414897093/"
    },
    {
      "time_played": "12:20",
      "artist": "FREDY BEDOYA",
      "title": "EL TIK TOK",
      "raw": "FREDY BEDOYA - EL TIK TOK",
      "link": null
    },
    {
      "time_played": "12:16",
      "artist": "DARIO GOMEZ",
      "title": "LA FIERA",
      "raw": "DARIO GOMEZ - LA FIERA",
      "link": "https://onlineradiobox.com/track/2089834577735395793/"
    },
    {
      "time_played": "12:13",
      "artist": "DARIO GOMEZ",
      "title": "POR LAS CALLES DEL AMOR",
      "raw": "DARIO GOMEZ - POR LAS CALLES DEL AMOR",
      "link": "https://onlineradiobox.com/track/810249609238286756/"
    },
    {
      "time_played": "12:11",
      "artist": "LOSCABALLEROS DE LA CANTINA",
      "title": "ADIOS ANGEL MIO",
      "raw": "LOSCABALLEROS DE LA CANTINA - ADIOS ANGEL MIO",
      "link": "https://onlineradiobox.com/track/360329536319127459/"
    },
    {
      "time_played": "12:11",
      "artist": "EL CHARRITO NEGRO",
      "title": "CORAZON TU LA ELEGISTE",
      "raw": "EL CHARRITO NEGRO - CORAZON TU LA ELEGISTE",
      "link": "https://onlineradiobox.com/track/2017759384954456525/"
    },
    {
      "time_played": "12:07",
      "artist": "MANDUKO",
      "title": "LA SUAVECITA",
      "raw": "MANDUKO - LA SUAVECITA",
      "link": "https://onlineradiobox.com/track/1801569021670119531/"
    },
    {
      "time_played": "12:03",
      "artist": "LUIS ALBERTO POSADA",
      "title": "EL PRECIO DE TU ERROR",
      "raw": "LUIS ALBERTO POSADA - EL PRECIO DE TU ERROR",
      "link": "https://onlineradiobox.com/track/144279535295142269/"
    },
    {
      "time_played": "12:01",
      "artist": "EL CHARRITO NEGRO",
      "title": "CORAZON TU LA ELEGISTE",
      "raw": "EL CHARRITO NEGRO - CORAZON TU LA ELEGISTE",
      "link": "https://onlineradiobox.com/track/2017759384954456525/"
    },
    {
      "time_played": "11:59",
      "artist": "YEISON JIMENEZ",
      "title": "MLP",
      "raw": "YEISON JIMENEZ - MLP",
      "link": "https://onlineradiobox.com/track/1945614817700603277/"
    },
    {
      "time_played": "11:56",
      "artist": "DARIO GOMEZ",
      "title": "OCUPARON TU LUGAR",
      "raw": "DARIO GOMEZ - OCUPARON TU LUGAR",
      "link": "https://onlineradiobox.com/track/2161945049402204349/"
    },
    {
      "time_played": "11:51",
      "artist": "LOS INQUIETOS",
      "title": "DI QUE SI.wav",
      "raw": "LOS INQUIETOS - DI QUE SI.wav",
      "link": null
    },
    {
      "time_played": "11:47",
      "artist": "LEO DIAZ",
      "title": "TE VAS Y VUELVES",
      "raw": "LEO DIAZ - TE VAS Y VUELVES",
      "link": "https://onlineradiobox.com/track/432457101081862504/"
    },
    {
      "time_played": "11:42",
      "artist": "EL BINOMIO DE ORO",
      "title": "DEJATE ATRAPAR.wav",
      "raw": "EL BINOMIO DE ORO - DEJATE ATRAPAR.wav",
      "link": "https://onlineradiobox.com/track/1513373833630174865/"
    },
    {
      "time_played": "11:39",
      "artist": "JHON JAIRO PEREZ",
      "title": "NO LLAMES A TU EX",
      "raw": "JHON JAIRO PEREZ - NO LLAMES A TU EX",
      "link": "https://onlineradiobox.com/track/288325047335269886/"
    },
    {
      "time_played": "11:37",
      "artist": "EL DESORDEN",
      "title": "EL DESORDEN.wav",
      "raw": "EL DESORDEN - EL DESORDEN.wav",
      "link": null
    },
    {
      "time_played": "11:37",
      "artist": "CELIA CRUZ",
      "title": "LA VIDA ES UN CARNAVAL",
      "raw": "CELIA CRUZ - LA VIDA ES UN CARNAVAL",
      "link": "https://onlineradiobox.com/track/1441298671212813713/"
    },
    {
      "time_played": "11:34",
      "artist": "EL CABALLERO GAUCHO",
      "title": "FLOR DE BULEVAR",
      "raw": "EL CABALLERO GAUCHO - FLOR DE BULEVAR",
      "link": "https://onlineradiobox.com/track/377904045022650862/"
    },
    {
      "time_played": "11:32",
      "artist": "JORGE CELEDON",
      "title": "MI LOCURA",
      "raw": "JORGE CELEDON - MI LOCURA",
      "link": "https://onlineradiobox.com/track/161731137033268410/"
    },
    {
      "time_played": "11:29",
      "artist": "CHE CHE MENDOZA",
      "title": "PENSANDO EN TI",
      "raw": "CHE CHE MENDOZA - PENSANDO EN TI",
      "link": "https://onlineradiobox.com/track/216249144367450498/"
    },
    {
      "time_played": "11:25",
      "artist": "LAS ESTRELLAS LATINAS",
      "title": "EN AQUELLOS A?OS",
      "raw": "LAS ESTRELLAS LATINAS - EN AQUELLOS A?OS",
      "link": "https://onlineradiobox.com/track/720705144244259960/"
    },
    {
      "time_played": "11:21",
      "artist": "LOS DIABLITOS",
      "title": "TU AMOR ES UN MILAGRO",
      "raw": "LOS DIABLITOS - TU AMOR ES UN MILAGRO",
      "link": "https://onlineradiobox.com/track/1297201038568391530/"
    },
    {
      "time_played": "11:17",
      "artist": "DARIO GOMEZ",
      "title": "SIN AMOR TAMBIEN SE VIVE - Dario Gomez..wav",
      "raw": "DARIO GOMEZ - SIN AMOR TAMBIEN SE VIVE - Dario Gomez..wav",
      "link": null
    },
    {
      "time_played": "11:13",
      "artist": "LOS CABALLEROSDE LA CANTINA",
      "title": "EL ENVIDIOSO.wav",
      "raw": "LOS CABALLEROSDE LA CANTINA - EL ENVIDIOSO.wav",
      "link": "https://onlineradiobox.com/track/827877634212482460/"
    },
    {
      "time_played": "11:10",
      "artist": "LOS HERMANOS BEDOYA",
      "title": "CORAZON DE PIEDRA",
      "raw": "LOS HERMANOS BEDOYA - CORAZON DE PIEDRA",
      "link": "https://onlineradiobox.com/track/2017776991144213707/"
    },
    {
      "time_played": "11:07",
      "artist": "DARIO GOMEZ",
      "title": "SATANAS",
      "raw": "DARIO GOMEZ - SATANAS",
      "link": "https://onlineradiobox.com/track/1873714614281047270/"
    },
    {
      "time_played": "11:05",
      "artist": "EL DESORDEN",
      "title": "EL DESORDEN.wav",
      "raw": "EL DESORDEN - EL DESORDEN.wav",
      "link": null
    },
    {
      "time_played": "11:01",
      "artist": "LOS DIABLITOS",
      "title": "TU AMOR ES UN MILAGRO",
      "raw": "LOS DIABLITOS - TU AMOR ES UN MILAGRO",
      "link": "https://onlineradiobox.com/track/1297201038568391530/"
    },
    {
      "time_played": "10:54",
      "artist": "EL BINOMIO DE ORO",
      "title": "COMO OLVIDARTE",
      "raw": "EL BINOMIO DE ORO - COMO OLVIDARTE",
      "link": "https://onlineradiobox.com/track/377903935167320300/"
    },
    {
      "time_played": "10:53",
      "artist": "EL DESORDEN",
      "title": "EL DESORDEN.wav",
      "raw": "EL DESORDEN - EL DESORDEN.wav",
      "link": null
    },
    {
      "time_played": "10:50",
      "artist": "ALEXIS ESCOBAR",
      "title": "EL INCOMPRENDIDO",
      "raw": "ALEXIS ESCOBAR - EL INCOMPRENDIDO",
      "link": "https://onlineradiobox.com/track/1729618109931922549/"
    },
    {
      "time_played": "10:47",
      "artist": "ALEXIS ESCOBAR",
      "title": "QUIEN SABE",
      "raw": "ALEXIS ESCOBAR - QUIEN SABE",
      "link": "https://onlineradiobox.com/track/2035228988304611367/"
    },
    {
      "time_played": "10:43",
      "artist": "GILDARDO MONTOYA",
      "title": "EL CARRATAPLAN",
      "raw": "GILDARDO MONTOYA - EL CARRATAPLAN",
      "link": "https://onlineradiobox.com/track/72186845230593151/"
    },
    {
      "time_played": "10:38",
      "artist": "GILDARDO MONTOYA",
      "title": "SE ENFERMO EL ARRUINAO",
      "raw": "GILDARDO MONTOYA - SE ENFERMO EL ARRUINAO",
      "link": "https://onlineradiobox.com/track/1225055897785129271/"
    },
    {
      "time_played": "10:38",
      "artist": "DARIO GOMEZ",
      "title": "DEBISTE SER MAS SINCERA",
      "raw": "DARIO GOMEZ - DEBISTE SER MAS SINCERA",
      "link": "https://onlineradiobox.com/track/864855478590657091/"
    },
    {
      "time_played": "10:37",
      "artist": "EL DESORDEN",
      "title": "EL DESORDEN.wav",
      "raw": "EL DESORDEN - EL DESORDEN.wav",
      "link": null
    },
    {
      "time_played": "10:37",
      "artist": "GILDARDO MONTOYA",
      "title": "SE ENFERMO EL ARRUINAO",
      "raw": "GILDARDO MONTOYA - SE ENFERMO EL ARRUINAO",
      "link": "https://onlineradiobox.com/track/1225055897785129271/"
    },
    {
      "time_played": "10:34",
      "artist": "EL DUETO DEL PUEBLO",
      "title": "LA VAGABUNDINA",
      "raw": "EL DUETO DEL PUEBLO - LA VAGABUNDINA",
      "link": "https://onlineradiobox.com/track/1369329979356581947/"
    },
    {
      "time_played": "10:29",
      "artist": "EL ANDARIEGO",
      "title": "LA FOTO DE LOS DOS",
      "raw": "EL ANDARIEGO - LA FOTO DE LOS DOS",
      "link": "https://onlineradiobox.com/track/1585449125164510820/"
    },
    {
      "time_played": "10:25",
      "artist": "LEO RODRIGUEZ",
      "title": "AMAR AMAR",
      "raw": "LEO RODRIGUEZ - AMAR AMAR",
      "link": "https://onlineradiobox.com/track/1657401830538586701/"
    },
    {
      "time_played": "10:20",
      "artist": "SERGIO VARGAS",
      "title": "NI TU NI YO",
      "raw": "SERGIO VARGAS - NI TU NI YO",
      "link": "https://onlineradiobox.com/track/1080905232284763505/"
    },
    {
      "time_played": "10:16",
      "artist": "EL DESORDEN",
      "title": "EL DESORDEN.wav",
      "raw": "EL DESORDEN - EL DESORDEN.wav",
      "link": null
    },
    {
      "time_played": "10:12",
      "artist": "OTTO SERGE Y RAFAEL RICARDO",
      "title": "ESPOSA MIA",
      "raw": "OTTO SERGE Y RAFAEL RICARDO - ESPOSA MIA",
      "link": "https://onlineradiobox.com/track/1225108260798124170/"
    },
    {
      "time_played": "10:08",
      "artist": "ARELYS HENAO",
      "title": "LA PATRONA",
      "raw": "ARELYS HENAO - LA PATRONA",
      "link": "https://onlineradiobox.com/track/755820213388387566/"
    },
    {
      "time_played": "10:06",
      "artist": "EL DESORDEN",
      "title": "EL DESORDEN.wav",
      "raw": "EL DESORDEN - EL DESORDEN.wav",
      "link": null
    },
    {
      "time_played": "10:06",
      "artist": "LOS DIABLITOS.wav",
      "title": "DEJALA",
      "raw": "LOS DIABLITOS.wav - DEJALA",
      "link": "https://onlineradiobox.com/track/1801481414167792445/"
    },
    {
      "time_played": "10:03",
      "artist": "LUIS TORRES",
      "title": "TAMBIEN SE ENOJA POR NADA",
      "raw": "LUIS TORRES - TAMBIEN SE ENOJA POR NADA",
      "link": "https://onlineradiobox.com/track/1620510922618214367/"
    },
    {
      "time_played": "09:58",
      "artist": "LOS DE YOLOMBO",
      "title": "EL BOBO",
      "raw": "LOS DE YOLOMBO - EL BOBO",
      "link": "https://onlineradiobox.com/track/1242595222382381111/"
    },
    {
      "time_played": "09:53",
      "artist": "DARIO GOMEZ.",
      "title": "ERES TODO EN MI VIDA",
      "raw": "DARIO GOMEZ. - ERES TODO EN MI VIDA",
      "link": "https://onlineradiobox.com/track/2179343821050392285/"
    },
    {
      "time_played": "09:49",
      "artist": "DARIO GOMEZ",
      "title": "ADIOS A LA VIDA",
      "raw": "DARIO GOMEZ - ADIOS A LA VIDA",
      "link": "https://onlineradiobox.com/track/1008970662397809404/"
    },
    {
      "time_played": "09:44",
      "artist": "JUAN GABRIEL",
      "title": "ME HE QUEDADO SOLO",
      "raw": "JUAN GABRIEL - ME HE QUEDADO SOLO",
      "link": "https://onlineradiobox.com/track/2161804496199281802/"
    },
    {
      "time_played": "09:39",
      "artist": "EL DESORDEN",
      "title": "EL DESORDEN.wav",
      "raw": "EL DESORDEN - EL DESORDEN.wav",
      "link": null
    },
    {
      "time_played": "09:36",
      "artist": "PASTOR LOPEZ",
      "title": "AMOR Y LLANTO.wav",
      "raw": "PASTOR LOPEZ - AMOR Y LLANTO.wav",
      "link": "https://onlineradiobox.com/track/17616448077809814/"
    },
    {
      "time_played": "09:32",
      "artist": "PASTOR LOPEZ",
      "title": "A?ORANZA FEBRIL",
      "raw": "PASTOR LOPEZ - A?ORANZA FEBRIL",
      "link": null
    },
    {
      "time_played": "09:27",
      "artist": "OMAR GELES",
      "title": "UNA HOJA EN BLANCO.wav",
      "raw": "OMAR GELES - UNA HOJA EN BLANCO.wav",
      "link": "https://onlineradiobox.com/track/1836683565573799100/"
    },
    {
      "time_played": "09:23",
      "artist": "HEREDERO",
      "title": "COQUETA",
      "raw": "HEREDERO - COQUETA",
      "link": "https://onlineradiobox.com/track/2089712510846799729/"
    },
    {
      "time_played": "09:20",
      "artist": "EL DESORDEN",
      "title": "EL DESORDEN.wav",
      "raw": "EL DESORDEN - EL DESORDEN.wav",
      "link": null
    },
    {
      "time_played": "09:17",
      "artist": "LOS CABALLEROS DE LA CANTINA",
      "title": "ME GASTO LA MIA",
      "raw": "LOS CABALLEROS DE LA CANTINA - ME GASTO LA MIA",
      "link": "https://onlineradiobox.com/track/594076726285744161/"
    },
    {
      "time_played": "09:14",
      "artist": "YEISON JIMENEZ",
      "title": "MALDITA TRAGA",
      "raw": "YEISON JIMENEZ - MALDITA TRAGA",
      "link": "https://onlineradiobox.com/track/2089852506617390488/"
    },
    {
      "time_played": "09:10",
      "artist": "LOS MILINDRINOS",
      "title": "LA PINGA PARA",
      "raw": "LOS MILINDRINOS - LA PINGA PARA",
      "link": "https://onlineradiobox.com/track/17616272079815681/"
    },
    {
      "time_played": "09:03",
      "artist": "LA COMBINACION VALLENATA",
      "title": "A PESAR DE TODO",
      "raw": "LA COMBINACION VALLENATA - A PESAR DE TODO",
      "link": "https://onlineradiobox.com/track/1674940736664328556/"
    },
    {
      "time_played": "08:56",
      "artist": "LUIS ALBERTO POSADA",
      "title": "TAN ILUSO",
      "raw": "LUIS ALBERTO POSADA - TAN ILUSO",
      "link": "https://onlineradiobox.com/track/1008917903877491082/"
    },
    {
      "time_played": "08:51",
      "artist": "EL GATO NEGRO",
      "title": "ME VOY PAR AOLVIDARTE",
      "raw": "EL GATO NEGRO - ME VOY PAR AOLVIDARTE",
      "link": "https://onlineradiobox.com/track/89673644604778768/"
    },
    {
      "time_played": "08:48",
      "artist": "LIZANDRO MEZA",
      "title": "SENDERITO DE AMOR",
      "raw": "LIZANDRO MEZA - SENDERITO DE AMOR",
      "link": "https://onlineradiobox.com/track/1746998194708529053/"
    },
    {
      "time_played": "08:44",
      "artist": "SILVIO BRITO",
      "title": "HISTORIA DE AMOR",
      "raw": "SILVIO BRITO - HISTORIA DE AMOR",
      "link": "https://onlineradiobox.com/track/792762704451592474/"
    },
    {
      "time_played": "08:40",
      "artist": "LOS PAMPEROS",
      "title": "QUE DIOS TE LO PAGUE",
      "raw": "LOS PAMPEROS - QUE DIOS TE LO PAGUE",
      "link": "https://onlineradiobox.com/track/2233879372511777151/"
    },
    {
      "time_played": "08:36",
      "artist": "DARIO GOMEZ",
      "title": "SIN AMOR TAMBIEN SE VIVE - Dario Gomez..wav",
      "raw": "DARIO GOMEZ - SIN AMOR TAMBIEN SE VIVE - Dario Gomez..wav",
      "link": null
    },
    {
      "time_played": "08:34",
      "artist": "RODOLFO",
      "title": "BORREMOS EL PASADO",
      "raw": "RODOLFO - BORREMOS EL PASADO",
      "link": "https://onlineradiobox.com/track/432457177400831870/"
    },
    {
      "time_played": "08:29",
      "artist": "DIOMEDES DIAS",
      "title": "FANTASIA",
      "raw": "DIOMEDES DIAS - FANTASIA",
      "link": null
    },
    {
      "time_played": "08:25",
      "artist": "NELSON HENR?QUEZ",
      "title": "EL BAION DE MADRID",
      "raw": "NELSON HENR?QUEZ - EL BAION DE MADRID",
      "link": "https://onlineradiobox.com/track/720653107503922322/"
    },
    {
      "time_played": "08:15",
      "artist": "PIPE BUENO",
      "title": "NO VOY A MORIR",
      "raw": "PIPE BUENO - NO VOY A MORIR",
      "link": "https://onlineradiobox.com/track/738191865733699954/"
    },
    {
      "time_played": "08:12",
      "artist": "GILDARDO MONTOYA",
      "title": "SE ENFERMO EL ARRUINAO",
      "raw": "GILDARDO MONTOYA - SE ENFERMO EL ARRUINAO",
      "link": "https://onlineradiobox.com/track/1225055897785129271/"
    },
    {
      "time_played": "08:05",
      "artist": "RODOLFO",
      "title": "CARI?ITO",
      "raw": "RODOLFO - CARI?ITO",
      "link": null
    },
    {
      "time_played": "08:01",
      "artist": "RODOLFO",
      "title": "BORREMOS EL PASADO",
      "raw": "RODOLFO - BORREMOS EL PASADO",
      "link": "https://onlineradiobox.com/track/432457177400831870/"
    },
    {
      "time_played": "07:55",
      "artist": "SONIA Y CARLOS",
      "title": "EL ERRANTE",
      "raw": "SONIA Y CARLOS - EL ERRANTE",
      "link": "https://onlineradiobox.com/track/1513373894812910261/"
    },
    {
      "time_played": "07:53",
      "artist": "EVELIO Y VIRGELINA",
      "title": "A?O Y MEDIO",
      "raw": "EVELIO Y VIRGELINA - A?O Y MEDIO",
      "link": "https://onlineradiobox.com/track/738192175914424939/"
    },
    {
      "time_played": "07:49",
      "artist": "CAMILO SEXTO",
      "title": "FRESA SALVAJE",
      "raw": "CAMILO SEXTO - FRESA SALVAJE",
      "link": "https://onlineradiobox.com/track/666169723667386345/"
    },
    {
      "time_played": "07:44",
      "artist": "RAFAEL OROZCO",
      "title": "DE RODILLAS.wav",
      "raw": "RAFAEL OROZCO - DE RODILLAS.wav",
      "link": null
    },
    {
      "time_played": "07:43",
      "artist": "JOHANNY AYALA",
      "title": "DE RODILLAS",
      "raw": "JOHANNY AYALA - DE RODILLAS",
      "link": null
    },
    {
      "time_played": "07:40",
      "artist": "OTTO SERGE",
      "title": "SIN TI",
      "raw": "OTTO SERGE - SIN TI",
      "link": "https://onlineradiobox.com/track/1513268267673286447/"
    },
    {
      "time_played": "07:35",
      "artist": "JOSE MU?OZ",
      "title": "EL HIJO DE ROSENDA",
      "raw": "JOSE MU?OZ - EL HIJO DE ROSENDA",
      "link": null
    },
    {
      "time_played": "07:31",
      "artist": "LOS RELICARIOS",
      "title": "METALE CANDELA A MONTE",
      "raw": "LOS RELICARIOS - METALE CANDELA A MONTE",
      "link": null
    },
    {
      "time_played": "07:22",
      "artist": "RAMIRO Y JOCHE",
      "title": "LA DUE?A DE MI SUERTE",
      "raw": "RAMIRO Y JOCHE - LA DUE?A DE MI SUERTE",
      "link": "https://onlineradiobox.com/track/1008970660119714280/"
    },
    {
      "time_played": "07:12",
      "artist": "ANTONIO AGUILAR",
      "title": "AY CHABELA",
      "raw": "ANTONIO AGUILAR - AY CHABELA",
      "link": "https://onlineradiobox.com/track/60925824/"
    },
    {
      "time_played": "07:09",
      "artist": "LOS BLANCO",
      "title": "DAME CANTINERO",
      "raw": "LOS BLANCO - DAME CANTINERO",
      "link": "https://onlineradiobox.com/track/1170537551876250171/"
    },
    {
      "time_played": "07:02",
      "artist": "DARIOGOMEZ",
      "title": "POR ESA MUJER.wav",
      "raw": "DARIOGOMEZ - POR ESA MUJER.wav",
      "link": null
    },
    {
      "time_played": "06:59",
      "artist": "DARIO GOMEZ",
      "title": "DEBISTE SER MAS SINCERA",
      "raw": "DARIO GOMEZ - DEBISTE SER MAS SINCERA",
      "link": "https://onlineradiobox.com/track/864855478590657091/"
    },
    {
      "time_played": "06:59",
      "artist": "EL GRUPO NICHE.",
      "title": "DEBIERA OLVIDARLA",
      "raw": "EL GRUPO NICHE. - DEBIERA OLVIDARLA",
      "link": "https://onlineradiobox.com/track/1945772310940624180/"
    },
    {
      "time_played": "06:52",
      "artist": "LORENZO ANTONIO",
      "title": "DOCE ROSAS",
      "raw": "LORENZO ANTONIO - DOCE ROSAS",
      "link": "https://onlineradiobox.com/track/38097119/"
    },
    {
      "time_played": "06:49",
      "artist": "LOS SORPRENDENTES",
      "title": "TANTO AMOR",
      "raw": "LOS SORPRENDENTES - TANTO AMOR",
      "link": "https://onlineradiobox.com/track/1513303408907415238/"
    },
    {
      "time_played": "06:45",
      "artist": "LOS RELICARIOS",
      "title": "MUJER TRAIDORA",
      "raw": "LOS RELICARIOS - MUJER TRAIDORA",
      "link": "https://onlineradiobox.com/track/1441298637658311462/"
    },
    {
      "time_played": "06:41",
      "artist": "JOSE MU?OZ",
      "title": "TE CASASTE TO?O",
      "raw": "JOSE MU?OZ - TE CASASTE TO?O",
      "link": null
    },
    {
      "time_played": "06:37",
      "artist": "JHONNY RIVERA",
      "title": "SE PERDONA SI SE QUIERE",
      "raw": "JHONNY RIVERA - SE PERDONA SI SE QUIERE",
      "link": "https://onlineradiobox.com/track/2161909853744832931/"
    },
    {
      "time_played": "06:33",
      "artist": "JHONNY RIVERA",
      "title": "EL DOLOR DE UNA PARTIDA",
      "raw": "JHONNY RIVERA - EL DOLOR DE UNA PARTIDA",
      "link": "https://onlineradiobox.com/track/432509910195238731/"
    },
    {
      "time_played": "06:29",
      "artist": "EL GRAN DAVID",
      "title": "PALOMA DEL ALMA MIA",
      "raw": "EL GRAN DAVID - PALOMA DEL ALMA MIA",
      "link": "https://onlineradiobox.com/track/792797881253286457/"
    },
    {
      "time_played": "06:28",
      "artist": "LOS BLANCO",
      "title": "DAME CANTINERO",
      "raw": "LOS BLANCO - DAME CANTINERO",
      "link": "https://onlineradiobox.com/track/1170537551876250171/"
    },
    {
      "time_played": "06:27",
      "artist": "JOSE MU?OZ",
      "title": "TE CASASTE TO?O",
      "raw": "JOSE MU?OZ - TE CASASTE TO?O",
      "link": null
    },
    {
      "time_played": "06:22",
      "artist": "LOS PECHICHONES",
      "title": "UN MOTIVO",
      "raw": "LOS PECHICHONES - UN MOTIVO",
      "link": "https://onlineradiobox.com/track/1225161127267464450/"
    },
    {
      "time_played": "06:17",
      "artist": "MIGUEL MORALES",
      "title": "OTRA PRIMAVERA",
      "raw": "MIGUEL MORALES - OTRA PRIMAVERA",
      "link": "https://onlineradiobox.com/track/144279534432651789/"
    },
    {
      "time_played": "06:13",
      "artist": "GABRIEL RAYMOND",
      "title": "SUFRIMIENTO.wav",
      "raw": "GABRIEL RAYMOND - SUFRIMIENTO.wav",
      "link": "https://onlineradiobox.com/track/1152998996769486702/"
    },
    {
      "time_played": "06:10",
      "artist": "EL CABALLERO GAUCHO",
      "title": "DERROTADO",
      "raw": "EL CABALLERO GAUCHO - DERROTADO",
      "link": null
    },
    {
      "time_played": "06:10",
      "artist": "JHON ALEX CASTA?O, JOSE ARBEY",
      "title": "PLATA POQUITA REMIX",
      "raw": "JHON ALEX CASTA?O, JOSE ARBEY - PLATA POQUITA REMIX",
      "link": null
    },
    {
      "time_played": "06:05",
      "artist": "FARID ORTIZ",
      "title": "ES MEJOR NO DECIRLO",
      "raw": "FARID ORTIZ - ES MEJOR NO DECIRLO",
      "link": "https://onlineradiobox.com/track/1441316227095501393/"
    },
    {
      "time_played": "06:02",
      "artist": "LOS RELICARIOS",
      "title": "EL AGUARDIENTERO",
      "raw": "LOS RELICARIOS - EL AGUARDIENTERO",
      "link": "https://onlineradiobox.com/track/1657489050997449697/"
    },
    {
      "time_played": "05:59",
      "artist": "LOS RELICARIOS",
      "title": "CAJON DE MADERA",
      "raw": "LOS RELICARIOS - CAJON DE MADERA",
      "link": "https://onlineradiobox.com/track/576572338924806733/"
    },
    {
      "time_played": "05:58",
      "artist": "ORESTES SINDICE",
      "title": "HIMNO NACIONAL COLOMBIA",
      "raw": "ORESTES SINDICE - HIMNO NACIONAL COLOMBIA",
      "link": null
    },
    {
      "time_played": "05:54",
      "artist": "RODOLFO AICARDI",
      "title": "TORMENTOS",
      "raw": "RODOLFO AICARDI - TORMENTOS",
      "link": "https://onlineradiobox.com/track/882307142706606436/"
    },
    {
      "time_played": "05:47",
      "artist": "NELSON VEL?SQUEZ",
      "title": "POR QUERER OLVIDARTE",
      "raw": "NELSON VEL?SQUEZ - POR QUERER OLVIDARTE",
      "link": "https://onlineradiobox.com/track/666134872900654348/"
    },
    {
      "time_played": "05:43",
      "artist": "LOS RAYOS",
      "title": "BILLETE VERDE",
      "raw": "LOS RAYOS - BILLETE VERDE",
      "link": "https://onlineradiobox.com/track/2161909846601343265/"
    },
    {
      "time_played": "05:40",
      "artist": "NELSON HENRIQUEZ",
      "title": "ENGA?ADORA",
      "raw": "NELSON HENRIQUEZ - ENGA?ADORA",
      "link": "https://onlineradiobox.com/track/882307069393792074/"
    },
    {
      "time_played": "05:37",
      "artist": "JHON JAIRO PEREZ",
      "title": "NO LLAMES A TU EX",
      "raw": "JHON JAIRO PEREZ - NO LLAMES A TU EX",
      "link": "https://onlineradiobox.com/track/288325047335269886/"
    },
    {
      "time_played": "05:32",
      "artist": "LOS TUPAMAROS",
      "title": "TU AUSENCIA",
      "raw": "LOS TUPAMAROS - TU AUSENCIA",
      "link": "https://onlineradiobox.com/track/936913136463995420/"
    },
    {
      "time_played": "05:28",
      "artist": "LOS GIGANTES DEL VALLENATO",
      "title": "EL ERROR",
      "raw": "LOS GIGANTES DEL VALLENATO - EL ERROR",
      "link": "https://onlineradiobox.com/track/1441316295393855066/"
    },
    {
      "time_played": "05:25",
      "artist": "EVELIO Y VIRGELINA",
      "title": "A?O Y MEDIO",
      "raw": "EVELIO Y VIRGELINA - A?O Y MEDIO",
      "link": "https://onlineradiobox.com/track/738192175914424939/"
    },
    {
      "time_played": "05:21",
      "artist": "LIZANDRO MESA.",
      "title": "ALEGRIA Y AMOR",
      "raw": "LIZANDRO MESA. - ALEGRIA Y AMOR",
      "link": "https://onlineradiobox.com/track/882307052963522758/"
    },
    {
      "time_played": "05:13",
      "artist": "ALEGRIA PARRANDERA",
      "title": "EL BOQUINCHE COMPRADORchimba pa mi",
      "raw": "ALEGRIA PARRANDERA - EL BOQUINCHE COMPRADORchimba pa mi",
      "link": null
    },
    {
      "time_played": "05:10",
      "artist": "ISMAEL MIRANDA",
      "title": "COPAS Y AMIGOS",
      "raw": "ISMAEL MIRANDA - COPAS Y AMIGOS",
      "link": "https://onlineradiobox.com/track/2089816985889967311/"
    },
    {
      "time_played": "05:05",
      "artist": "DIOMEDES DIAZ",
      "title": "AMARTE MAS NO PUDE",
      "raw": "DIOMEDES DIAZ - AMARTE MAS NO PUDE",
      "link": "https://onlineradiobox.com/track/1513426873525522126/"
    },
    {
      "time_played": "04:57",
      "artist": "LOS RELICARIOS",
      "title": "BEBIENDO Y RECORDANDO",
      "raw": "LOS RELICARIOS - BEBIENDO Y RECORDANDO",
      "link": "https://onlineradiobox.com/track/594076653207354465/"
    },
    {
      "time_played": "04:53",
      "artist": "SILVESTRE DANGON",
      "title": "A BLANCO Y NEGRO",
      "raw": "SILVESTRE DANGON - A BLANCO Y NEGRO",
      "link": "https://onlineradiobox.com/track/360364782668603209/"
    },
    {
      "time_played": "04:49",
      "artist": "DARIO GOMEZ",
      "title": "SIN AMOR TAMBIEN SE VIVE - Dario Gomez..wav",
      "raw": "DARIO GOMEZ - SIN AMOR TAMBIEN SE VIVE - Dario Gomez..wav",
      "link": null
    },
    {
      "time_played": "04:47",
      "artist": "DARIO GOMEZ",
      "title": "NOSTALGIA DEL AYER",
      "raw": "DARIO GOMEZ - NOSTALGIA DEL AYER",
      "link": "https://onlineradiobox.com/track/1225143446616671513/"
    },
    {
      "time_played": "04:39",
      "artist": "YEISON JIMENEZ",
      "title": "TENIAS RAZON.wav",
      "raw": "YEISON JIMENEZ - TENIAS RAZON.wav",
      "link": "https://onlineradiobox.com/track/233788941628804585/"
    },
    {
      "time_played": "04:33",
      "artist": "FANTASMAS DEL CARIBE",
      "title": "POR UNA LAGRIMA",
      "raw": "FANTASMAS DEL CARIBE - POR UNA LAGRIMA",
      "link": "https://onlineradiobox.com/track/2017777002736570776/"
    },
    {
      "time_played": "04:28",
      "artist": "HECTOR LAVOE",
      "title": "LA VIDA ES BONITA",
      "raw": "HECTOR LAVOE - LA VIDA ES BONITA",
      "link": "https://onlineradiobox.com/track/432387137456701727/"
    },
    {
      "time_played": "04:24",
      "artist": "LOS DIABLITOS",
      "title": "POR UNA MENTIRA.wav",
      "raw": "LOS DIABLITOS - POR UNA MENTIRA.wav",
      "link": "https://onlineradiobox.com/track/432439943026641858/"
    },
    {
      "time_played": "04:21",
      "artist": "VITIN AVILES",
      "title": "TEMES",
      "raw": "VITIN AVILES - TEMES",
      "link": "https://onlineradiobox.com/track/1297130663486211098/"
    },
    {
      "time_played": "04:17",
      "artist": "LISANDRO MEZA",
      "title": "LLORO Y CANTO",
      "raw": "LISANDRO MEZA - LLORO Y CANTO",
      "link": "https://onlineradiobox.com/track/1153050634496183614/"
    },
    {
      "time_played": "04:12",
      "artist": "LOS INQUIETOS DEL VALLENATO",
      "title": "SI TU ESTUVIERAS",
      "raw": "LOS INQUIETOS DEL VALLENATO - SI TU ESTUVIERAS",
      "link": "https://onlineradiobox.com/track/72204353775993496/"
    },
    {
      "time_played": "04:09",
      "artist": "JOHNNY RIVERA",
      "title": "EL INTENSO",
      "raw": "JOHNNY RIVERA - EL INTENSO",
      "link": null
    },
    {
      "time_played": "04:06",
      "artist": "JOAN SEBASTIAN",
      "title": "HASTA QUE AMANEZCA",
      "raw": "JOAN SEBASTIAN - HASTA QUE AMANEZCA",
      "link": "https://onlineradiobox.com/track/954364859565608564/"
    },
    {
      "time_played": "04:01",
      "artist": "LUIS ALBERTO POSADA",
      "title": "BEBIENDO POR TI",
      "raw": "LUIS ALBERTO POSADA - BEBIENDO POR TI",
      "link": "https://onlineradiobox.com/track/1008988360342218405/"
    },
    {
      "time_played": "03:58",
      "artist": "HERNAN HERNANDEZ",
      "title": "TONTO AMOR",
      "raw": "HERNAN HERNANDEZ - TONTO AMOR",
      "link": "https://onlineradiobox.com/track/1657471612616557908/"
    },
    {
      "time_played": "03:53",
      "artist": "MIGUEL MOLY",
      "title": "JUNTO A TU CORAZON",
      "raw": "MIGUEL MOLY - JUNTO A TU CORAZON",
      "link": "https://onlineradiobox.com/track/105054389/"
    },
    {
      "time_played": "03:50",
      "artist": "EL CHAKAL DEL SUR",
      "title": "EL AMOR Y LA FELICIDAD",
      "raw": "EL CHAKAL DEL SUR - EL AMOR Y LA FELICIDAD",
      "link": "https://onlineradiobox.com/track/611704926353876334/"
    },
    {
      "time_played": "03:44",
      "artist": "ENALDO BARRERA",
      "title": "SI NO PELIAMOS TANTO",
      "raw": "ENALDO BARRERA - SI NO PELIAMOS TANTO",
      "link": null
    },
    {
      "time_played": "03:41",
      "artist": "EL ANDARIEGO",
      "title": "QUE EST?S BUSCANDO",
      "raw": "EL ANDARIEGO - QUE EST?S BUSCANDO",
      "link": "https://onlineradiobox.com/track/1242595272643334863/"
    },
    {
      "time_played": "03:38",
      "artist": "EL ANDARIEGO",
      "title": "DOS DIAS",
      "raw": "EL ANDARIEGO - DOS DIAS",
      "link": "https://onlineradiobox.com/track/720617428168484897/"
    },
    {
      "time_played": "03:34",
      "artist": "PASTOR LOPEZ",
      "title": "PECADOR",
      "raw": "PASTOR LOPEZ - PECADOR",
      "link": null
    },
    {
      "time_played": "03:28",
      "artist": "WILLIE COLON",
      "title": "ASIA",
      "raw": "WILLIE COLON - ASIA",
      "link": null
    },
    {
      "time_played": "03:26",
      "artist": "LUIS ALFONSO",
      "title": "CONTENTOSO",
      "raw": "LUIS ALFONSO - CONTENTOSO",
      "link": "https://onlineradiobox.com/track/522019942830195095/"
    },
    {
      "time_played": "03:21",
      "artist": "JOE ARROYO",
      "title": "LA TORTUGA",
      "raw": "JOE ARROYO - LA TORTUGA",
      "link": "https://onlineradiobox.com/track/1369223457515935288/"
    },
    {
      "time_played": "03:19",
      "artist": "LOS BLANCO",
      "title": "DAME CANTINERO",
      "raw": "LOS BLANCO - DAME CANTINERO",
      "link": "https://onlineradiobox.com/track/1170537551876250171/"
    },
    {
      "time_played": "03:15",
      "artist": "VICENTE FERNANDEZ",
      "title": "AUNQUE MAL PAGEN ELLAS",
      "raw": "VICENTE FERNANDEZ - AUNQUE MAL PAGEN ELLAS",
      "link": "https://onlineradiobox.com/track/1530825646416986680/"
    },
    {
      "time_played": "03:12",
      "artist": "DIOMEDES DIAZ",
      "title": "SIMULACION",
      "raw": "DIOMEDES DIAZ - SIMULACION",
      "link": "https://onlineradiobox.com/track/216319540248515305/"
    },
    {
      "time_played": "03:08",
      "artist": "EL CHARRITO NEGRO",
      "title": "CON UN ADIOS - .wav",
      "raw": "EL CHARRITO NEGRO - CON UN ADIOS - .wav",
      "link": "https://onlineradiobox.com/track/666134813484081814/"
    },
    {
      "time_played": "03:05",
      "artist": "CUARTETO CONTINENTAL",
      "title": "LLORANDO SE FUE",
      "raw": "CUARTETO CONTINENTAL - LLORANDO SE FUE",
      "link": "https://onlineradiobox.com/track/2089816988478981799/"
    },
    {
      "time_played": "03:00",
      "artist": "WILLIE COLON",
      "title": "IDILIO",
      "raw": "WILLIE COLON - IDILIO",
      "link": "https://onlineradiobox.com/track/1225143478371200573/"
    },
    {
      "time_played": "02:55",
      "artist": "LA DECISION VALLENATA",
      "title": "AMOR SIN FRONTERAS..wav",
      "raw": "LA DECISION VALLENATA - AMOR SIN FRONTERAS..wav",
      "link": "https://onlineradiobox.com/track/738192012527779597/"
    },
    {
      "time_played": "02:51",
      "artist": "FERNANDO BURBANO",
      "title": "EL PRINCIPE",
      "raw": "FERNANDO BURBANO - EL PRINCIPE",
      "link": "https://onlineradiobox.com/track/2017776979745689046/"
    },
    {
      "time_played": "02:47",
      "artist": "RODOLFO AICARDI",
      "title": "TORMENTOS",
      "raw": "RODOLFO AICARDI - TORMENTOS",
      "link": "https://onlineradiobox.com/track/882307142706606436/"
    },
    {
      "time_played": "02:42",
      "artist": "EDDY HERRERA",
      "title": "A DORMIR JUNTITOS",
      "raw": "EDDY HERRERA - A DORMIR JUNTITOS",
      "link": "https://onlineradiobox.com/track/35248995/"
    },
    {
      "time_played": "02:40",
      "artist": "YEISON JIMENEZ",
      "title": "MLP",
      "raw": "YEISON JIMENEZ - MLP",
      "link": "https://onlineradiobox.com/track/1945614817700603277/"
    },
    {
      "time_played": "02:37",
      "artist": "YEISON JIMENEZ",
      "title": "MALDITA TRAGA",
      "raw": "YEISON JIMENEZ - MALDITA TRAGA",
      "link": "https://onlineradiobox.com/track/2089852506617390488/"
    },
    {
      "time_played": "02:33",
      "artist": "GRUPO MARINA PERLA",
      "title": "AL CALOR DE LA CUMBIA",
      "raw": "GRUPO MARINA PERLA - AL CALOR DE LA CUMBIA",
      "link": "https://onlineradiobox.com/track/810249494054566675/"
    },
    {
      "time_played": "02:28",
      "artist": "FARID ORTIZ",
      "title": "DE QUE TE BESO TE BESO",
      "raw": "FARID ORTIZ - DE QUE TE BESO TE BESO",
      "link": "https://onlineradiobox.com/track/936913067123957617/"
    },
    {
      "time_played": "02:25",
      "artist": "JUAN CARLOS HURTADO EL ANDARIEGO",
      "title": "EL AMOR NO TIENE EDAD",
      "raw": "JUAN CARLOS HURTADO EL ANDARIEGO - EL AMOR NO TIENE EDAD",
      "link": "https://onlineradiobox.com/track/1657524270900431016/"
    },
    {
      "time_played": "02:21",
      "artist": "EL GRAN COMBO DE PUERTO RICO",
      "title": "TE REGALO EL CORAZON",
      "raw": "EL GRAN COMBO DE PUERTO RICO - TE REGALO EL CORAZON",
      "link": "https://onlineradiobox.com/track/576554724037023904/"
    },
    {
      "time_played": "02:17",
      "artist": "ARMANDO HERNANDEZ",
      "title": "POR RETENERTE",
      "raw": "ARMANDO HERNANDEZ - POR RETENERTE",
      "link": null
    },
    {
      "time_played": "02:13",
      "artist": "DARIO GOMEZ",
      "title": "LA PENA ES HONDA",
      "raw": "DARIO GOMEZ - LA PENA ES HONDA",
      "link": "https://onlineradiobox.com/track/1873644195642359911/"
    },
    {
      "time_played": "02:08",
      "artist": "LOS CHICHES DEL VALLENATO",
      "title": "SI ELLA SUPIERA",
      "raw": "LOS CHICHES DEL VALLENATO - SI ELLA SUPIERA",
      "link": "https://onlineradiobox.com/track/1873661815060541463/"
    },
    {
      "time_played": "02:06",
      "artist": "LOS BLANCO",
      "title": "MORENA CONSENTIDA",
      "raw": "LOS BLANCO - MORENA CONSENTIDA",
      "link": "https://onlineradiobox.com/track/1080940592948001618/"
    },
    {
      "time_played": "02:02",
      "artist": "HERNAN GOMEZ",
      "title": "LA CANTINA",
      "raw": "HERNAN GOMEZ - LA CANTINA",
      "link": "https://onlineradiobox.com/track/2052856442999694207/"
    },
    {
      "time_played": "01:57",
      "artist": "EL BINOMIO DE ORO",
      "title": "MI SEGUNDO VIDA",
      "raw": "EL BINOMIO DE ORO - MI SEGUNDO VIDA",
      "link": "https://onlineradiobox.com/track/1441193285977909915/"
    },
    {
      "time_played": "01:53",
      "artist": "FRUKO Y SUS TESOS",
      "title": "MANYOMA",
      "raw": "FRUKO Y SUS TESOS - MANYOMA",
      "link": "https://onlineradiobox.com/track/1026422279967459667/"
    },
    {
      "time_played": "01:50",
      "artist": "LOS CABALLEROSDE LA CANTINA",
      "title": "EL ENVIDIOSO.wav",
      "raw": "LOS CABALLEROSDE LA CANTINA - EL ENVIDIOSO.wav",
      "link": "https://onlineradiobox.com/track/827877634212482460/"
    },
    {
      "time_played": "01:46",
      "artist": "EL COMBO DE LAS ESTRELLAS",
      "title": "AMOR A PRIMERA VISTA",
      "raw": "EL COMBO DE LAS ESTRELLAS - AMOR A PRIMERA VISTA",
      "link": "https://onlineradiobox.com/track/89673522731906996/"
    },
    {
      "time_played": "01:42",
      "artist": "RIKARENA",
      "title": "TE VOY A HACER FALTA",
      "raw": "RIKARENA - TE VOY A HACER FALTA",
      "link": "https://onlineradiobox.com/track/161731353134869938/"
    },
    {
      "time_played": "01:37",
      "artist": "LOS GENIOS DEL VALLENATO",
      "title": "MALO",
      "raw": "LOS GENIOS DEL VALLENATO - MALO",
      "link": "https://onlineradiobox.com/track/936877899772102338/"
    },
    {
      "time_played": "01:34",
      "artist": "JOAQUIN GUILLER & MAICOL ROSERO",
      "title": "NO SUFRIRE POR NADIE",
      "raw": "JOAQUIN GUILLER & MAICOL ROSERO - NO SUFRIRE POR NADIE",
      "link": null
    },
    {
      "time_played": "01:31",
      "artist": "DARIO GOMEZ",
      "title": "SATANAS",
      "raw": "DARIO GOMEZ - SATANAS",
      "link": "https://onlineradiobox.com/track/1873714614281047270/"
    },
    {
      "time_played": "01:28",
      "artist": "LUIS ALBERTO POSADA",
      "title": "ME TOMAS Y ME DEJAS",
      "raw": "LUIS ALBERTO POSADA - ME TOMAS Y ME DEJAS",
      "link": "https://onlineradiobox.com/track/59452138/"
    },
    {
      "time_played": "01:24",
      "artist": "LUIS ALBERTO POSADA",
      "title": "MI PASION RECORDARAS",
      "raw": "LUIS ALBERTO POSADA - MI PASION RECORDARAS",
      "link": "https://onlineradiobox.com/track/576607502688399090/"
    },
    {
      "time_played": "01:21",
      "artist": "PASTOR LOPEZ",
      "title": "NUESTRO ANILLITO",
      "raw": "PASTOR LOPEZ - NUESTRO ANILLITO",
      "link": "https://onlineradiobox.com/track/1729564392732090147/"
    },
    {
      "time_played": "01:18",
      "artist": "THE LATIN BROTHERS",
      "title": "SOBRE LAS OLAS",
      "raw": "THE LATIN BROTHERS - SOBRE LAS OLAS",
      "link": "https://onlineradiobox.com/track/1314688042161505348/"
    },
    {
      "time_played": "01:15",
      "artist": "MARCO ANTONIO SOLIS",
      "title": "LA VENIA BENDITA",
      "raw": "MARCO ANTONIO SOLIS - LA VENIA BENDITA",
      "link": "https://onlineradiobox.com/track/504497084197268702/"
    },
    {
      "time_played": "01:11",
      "artist": "LAS KETCHUP",
      "title": "CARRAPICHO",
      "raw": "LAS KETCHUP - CARRAPICHO",
      "link": null
    },
    {
      "time_played": "01:08",
      "artist": "LOS MELODICOS",
      "title": "YO QUIERO VERLA ESTA NOCHE",
      "raw": "LOS MELODICOS - YO QUIERO VERLA ESTA NOCHE",
      "link": "https://onlineradiobox.com/track/360452316164938868/"
    },
    {
      "time_played": "01:04",
      "artist": "VICENTE FERNANDEZ",
      "title": "POR TU MALDITO AMOR",
      "raw": "VICENTE FERNANDEZ - POR TU MALDITO AMOR",
      "link": "https://onlineradiobox.com/track/55206418/"
    },
    {
      "time_played": "00:59",
      "artist": "RAMIRO Y JOCHE",
      "title": "CON QUE DERECHO",
      "raw": "RAMIRO Y JOCHE - CON QUE DERECHO",
      "link": "https://onlineradiobox.com/track/1080958129880624377/"
    },
    {
      "time_played": "00:56",
      "artist": "ARELYS HENAO",
      "title": "MUJERES Y DESPECHO 2024",
      "raw": "ARELYS HENAO - MUJERES Y DESPECHO 2024",
      "link": "https://onlineradiobox.com/track/648595709239073808/"
    },
    {
      "time_played": "00:53",
      "artist": "LOS WARAHUACO",
      "title": "ATREVETE A MIRARME DE FRENTE",
      "raw": "LOS WARAHUACO - ATREVETE A MIRARME DE FRENTE",
      "link": "https://onlineradiobox.com/track/216355039174462952/"
    },
    {
      "time_played": "00:48",
      "artist": "FRUKO Y SUS TESOS",
      "title": "LOS CHARCOS",
      "raw": "FRUKO Y SUS TESOS - LOS CHARCOS",
      "link": "https://onlineradiobox.com/track/720652287085702320/"
    },
    {
      "time_played": "00:43",
      "artist": "JORGECELEDON",
      "title": "NO TE OLVIDARE.wav",
      "raw": "JORGECELEDON - NO TE OLVIDARE.wav",
      "link": null
    },
    {
      "time_played": "00:40",
      "artist": "EL CHARRITO NEGRO",
      "title": "A PUNTA DE TRAGO",
      "raw": "EL CHARRITO NEGRO - A PUNTA DE TRAGO",
      "link": "https://onlineradiobox.com/track/2035228798258728316/"
    },
    {
      "time_played": "00:37",
      "artist": "EL CHARRITO NEGRO",
      "title": "OJALA Y TE DURE.wav",
      "raw": "EL CHARRITO NEGRO - OJALA Y TE DURE.wav",
      "link": "https://onlineradiobox.com/track/2233968036505681343/"
    },
    {
      "time_played": "00:34",
      "artist": "EDGAR LEANDRO",
      "title": "LA REVANCHA",
      "raw": "EDGAR LEANDRO - LA REVANCHA",
      "link": "https://onlineradiobox.com/track/1225143478657933348/"
    },
    {
      "time_played": "00:29",
      "artist": "SERGIO VARGAS",
      "title": "PENAS AL VIENTO",
      "raw": "SERGIO VARGAS - PENAS AL VIENTO",
      "link": "https://onlineradiobox.com/track/504514711394713946/"
    },
    {
      "time_played": "00:26",
      "artist": "LOS RAYOS",
      "title": "BILLETE VERDE",
      "raw": "LOS RAYOS - BILLETE VERDE",
      "link": "https://onlineradiobox.com/track/2161909846601343265/"
    },
    {
      "time_played": "00:22",
      "artist": "LOS DE AQUINO.",
      "title": "LAS CORCHOLATAS",
      "raw": "LOS DE AQUINO. - LAS CORCHOLATAS",
      "link": null
    },
    {
      "time_played": "00:17",
      "artist": "DIOMEDES DIAZ Y JUANCHO ROIS",
      "title": "DEJALA",
      "raw": "DIOMEDES DIAZ Y JUANCHO ROIS - DEJALA",
      "link": "https://onlineradiobox.com/track/1225108268155643738/"
    },
    {
      "time_played": "00:15",
      "artist": "CIRO QUI?ONEZ",
      "title": "REGALADA SALES CARA REMIX",
      "raw": "CIRO QUI?ONEZ - REGALADA SALES CARA REMIX",
      "link": null
    },
    {
      "time_played": "00:12",
      "artist": "NELSON Y SUS ESTRELLAS",
      "title": "EL EMPERADORCITO",
      "raw": "NELSON Y SUS ESTRELLAS - EL EMPERADORCITO",
      "link": "https://onlineradiobox.com/track/1945613828881381699/"
    },
    {
      "time_played": "00:08",
      "artist": "ARMANDO HERNANDEZ",
      "title": "SIN ALMA Y SIN CORAZON",
      "raw": "ARMANDO HERNANDEZ - SIN ALMA Y SIN CORAZON",
      "link": "https://onlineradiobox.com/track/1080975463655777085/"
    },
    {
      "time_played": "00:05",
      "artist": "DARIO GOMEZ",
      "title": "ASI SE LE CANTA AL DESPECHO",
      "raw": "DARIO GOMEZ - ASI SE LE CANTA AL DESPECHO",
      "link": "https://onlineradiobox.com/track/1225090636719253125/"
    },
    {
      "time_played": "00:01",
      "artist": "RODOLFO CON LOS HISPANOS",
      "title": "OJITOS HECHICEROS",
      "raw": "RODOLFO CON LOS HISPANOS - OJITOS HECHICEROS",
      "link": "https://onlineradiobox.com/track/1008970685714847305/"
    }
  ]
}